concurrency_client/__init__.py
concurrency_client/api_pool.py
concurrency_client/chat_client.py
concurrency_client/platform.py
concurrency_client/universal_api_client.py
concurrency_client/utils.py
concurrency_client-0.1.2.dist-info/METADATA
concurrency_client-0.1.2.dist-info/WHEEL
concurrency_client-0.1.2.dist-info/top_level.txt
concurrency_client-0.1.2.dist-info/RECORD
