Metadata-Version: 2.4
Name: concurrency-client
Version: 0.1.2
Summary: A lightweight, reusable concurrency-friendly client facade for OpenAI-compatible chat APIs
Author-email: Zhao Jian <2406753447@qq.com>
License: MIT License
Keywords: llm,openai,chat,concurrency,async
Classifier: Programming Language :: Python :: 3
Classifier: Programming Language :: Python :: 3 :: Only
Classifier: Programming Language :: Python :: 3.9
Classifier: License :: OSI Approved :: MIT License
Classifier: Operating System :: OS Independent
Requires-Python: >=3.9
Requires-Dist: openai>=1.0.0
